{
  "gitSyncId": "68526bd92a1f661159df310f_6916f883-02d8-4910-913f-7b2e0aed4021",
  "id": "Page1_Auth.isAdmin",
  "pluginId": "js-plugin",
  "pluginType": "JS",
  "unpublishedAction": {
    "actionConfiguration": {
      "encodeParamsToggle": true,
      "jsArguments": [],
      "paginationType": "NONE",
      "timeoutInMillisecond": 10000
    },
    "collectionId": "Page1_Auth",
    "confirmBeforeExecute": false,
    "datasource": {
      "isAutoGenerated": false,
      "name": "UNUSED_DATASOURCE",
      "pluginId": "js-plugin"
    },
    "dynamicBindingPathList": [
      {
        "key": "body"
      }
    ],
    "fullyQualifiedName": "Auth.isAdmin",
    "name": "isAdmin",
    "pageId": "Page1",
    "runBehaviour": "MANUAL",
    "userSetOnLoad": false
  }
}