{
  "animateLoading": true,
  "borderRadius": "{{appsmith.theme.borderRadius.appBorderRadius}}",
  "bottomRow": 371,
  "boxShadow": "none",
  "canEscapeKeyClose": true,
  "canOutsideClickClose": true,
  "children": [
    {
      "borderRadius": "{{appsmith.theme.borderRadius.appBorderRadius}}",
      "bottomRow": 310,
      "boxShadow": "{{appsmith.theme.boxShadow.appBoxShadow}}",
      "canExtend": true,
      "detachFromLayout": true,
      "dynamicBindingPathList": [
        {
          "key": "borderRadius"
        },
        {
          "key": "boxShadow"
        }
      ],
      "dynamicHeight": "AUTO_HEIGHT",
      "flexLayers": [],
      "isDisabled": false,
      "isLoading": false,
      "isVisible": true,
      "key": "j9d01n3gd6",
      "leftColumn": 0,
      "maxDynamicHeight": 9000,
      "minDynamicHeight": 4,
      "minHeight": 240,
      "minWidth": 450,
      "mobileBottomRow": 240,
      "mobileLeftColumn": 0,
      "mobileRightColumn": 705.75,
      "mobileTopRow": 0,
      "needsErrorInfo": false,
      "parentColumnSpace": 1,
      "parentId": "hk8qnwjs6t",
      "parentRowSpace": 1,
      "renderMode": "CANVAS",
      "responsiveBehavior": "fill",
      "rightColumn": 705.75,
      "shouldScrollContents": false,
      "topRow": 0,
      "type": "CANVAS_WIDGET",
      "version": 1,
      "widgetId": "rri4y3v07o",
      "widgetName": "Canvas2"
    }
  ],
  "detachFromLayout": true,
  "dynamicBindingPathList": [
    {
      "key": "borderRadius"
    }
  ],
  "dynamicHeight": "AUTO_HEIGHT",
  "height": 310,
  "isCanvas": true,
  "isLoading": false,
  "key": "4tfertg6ch",
  "leftColumn": 12,
  "maxDynamicHeight": 9000,
  "minDynamicHeight": 24,
  "mobileBottomRow": 85,
  "mobileLeftColumn": 12,
  "mobileRightColumn": 36,
  "mobileTopRow": 61,
  "needsErrorInfo": false,
  "parentColumnSpace": 29.40625,
  "parentId": "0",
  "parentRowSpace": 10,
  "renderMode": "CANVAS",
  "rightColumn": 36,
  "shouldScrollContents": true,
  "topRow": 61,
  "type": "MODAL_WIDGET",
  "version": 2,
  "widgetId": "hk8qnwjs6t",
  "widgetName": "ModalAddUser",
  "width": 456
}